hieroglyphe/__init__.py
hieroglyphe/hieroglyphe.py
pyhieroglyphe-0.1.0.dist-info/METADATA
pyhieroglyphe-0.1.0.dist-info/WHEEL
pyhieroglyphe-0.1.0.dist-info/top_level.txt
pyhieroglyphe-0.1.0.dist-info/RECORD
