Metadata-Version: 2.4
Name: pyhieroglyphe
Version: 0.1.0
Summary: Librairie de traduction français → hiéroglyphes
Author: editor4001
Author-email: 30leodomingue@gmail.com
Classifier: Programming Language :: Python :: 3
Classifier: License :: OSI Approved :: MIT License
Classifier: Operating System :: OS Independent
Requires-Python: >=3.6
Dynamic: author
Dynamic: author-email
Dynamic: classifier
Dynamic: description
Dynamic: description-content-type
Dynamic: requires-python
Dynamic: summary
